.gitignore
.gitmodules
LICENSE
README.md
config.yaml
requirements.txt
setup.py
.vscode/settings.json
html/twitchAuth.php
src/retroBot/__init__.py
src/retroBot/bot.py
src/retroBot/channelHandler.py
src/retroBot/config.py
src/retroBot/emotes.py
src/retroBot/message.py
src/retroBot/userAuth.py
src/retroBot.egg-info/PKG-INFO
src/retroBot.egg-info/SOURCES.txt
src/retroBot.egg-info/dependency_links.txt
src/retroBot.egg-info/requires.txt
src/retroBot.egg-info/top_level.txt