Metadata-Version: 2.1
Name: retroBot
Version: 0.3.3
Summary: A Twitch IRC bot integrating twitchAPI and irc
Home-page: https://github.com/retrontology/retroBot
Author: retrontology
Author-email: retrontology@hotmail.com
Project-URL: Bug Tracker, https://github.com/retrontology/retroBot/issues
Classifier: Programming Language :: Python :: 3
Classifier: Operating System :: OS Independent
Requires-Python: >=3.6
License-File: LICENSE
